google_cloud_automlops/AutoMLOps.py
google_cloud_automlops/__init__.py
google_cloud_automlops/deployments/__init__.py
google_cloud_automlops/deployments/base.py
google_cloud_automlops/deployments/cloudbuild.py
google_cloud_automlops/deployments/github_actions.py
google_cloud_automlops/deployments/templates/__init__.py
google_cloud_automlops/deployments/templates/cloudbuild/__init__.py
google_cloud_automlops/deployments/templates/cloudbuild/cloudbuild.yaml.j2
google_cloud_automlops/deployments/templates/github_actions/__init__.py
google_cloud_automlops/deployments/templates/github_actions/github_actions.yaml.j2
google_cloud_automlops/orchestration/__init__.py
google_cloud_automlops/orchestration/base.py
google_cloud_automlops/orchestration/kfp.py
google_cloud_automlops/orchestration/templates/__init__.py
google_cloud_automlops/orchestration/templates/kfp/README.md.j2
google_cloud_automlops/orchestration/templates/kfp/__init__.py
google_cloud_automlops/orchestration/templates/kfp/components/__init__.py
google_cloud_automlops/orchestration/templates/kfp/components/component_base/Dockerfile.j2
google_cloud_automlops/orchestration/templates/kfp/components/component_base/__init__.py
google_cloud_automlops/orchestration/templates/kfp/components/component_base/src/__init__.py
google_cloud_automlops/orchestration/templates/kfp/components/component_base/src/task.py.j2
google_cloud_automlops/orchestration/templates/kfp/model_monitoring/__init__.py
google_cloud_automlops/orchestration/templates/kfp/model_monitoring/monitor.py.j2
google_cloud_automlops/orchestration/templates/kfp/model_monitoring/requirements.txt.j2
google_cloud_automlops/orchestration/templates/kfp/pipelines/__init__.py
google_cloud_automlops/orchestration/templates/kfp/pipelines/pipeline.py.j2
google_cloud_automlops/orchestration/templates/kfp/pipelines/pipeline_runner.py.j2
google_cloud_automlops/orchestration/templates/kfp/pipelines/requirements.txt.j2
google_cloud_automlops-1.3.3.dist-info/LICENSE
google_cloud_automlops-1.3.3.dist-info/METADATA
google_cloud_automlops-1.3.3.dist-info/WHEEL
google_cloud_automlops-1.3.3.dist-info/top_level.txt
google_cloud_automlops-1.3.3.dist-info/RECORD
