Metadata-Version: 2.1
Name: google-cloud-automlops
Version: 1.3.3
Summary: Build MLOps Pipelines in Minutes.
Home-page: https://github.com/GoogleCloudPlatform/automlops
Author: Sean Rastatter
Author-email: srastatter@google.com
License: Apache-2.0
Classifier: Development Status :: 5 - Production/Stable
Classifier: Intended Audience :: Developers
Classifier: License :: OSI Approved :: Apache Software License
Classifier: Operating System :: POSIX :: Linux
Classifier: Operating System :: MacOS :: MacOS X
Classifier: Natural Language :: English
Classifier: Programming Language :: Python :: 3.7
Classifier: Programming Language :: Python :: 3.8
Classifier: Programming Language :: Python :: 3.9
Classifier: Programming Language :: Python :: 3.10
Requires-Python: >=3.7
License-File: LICENSE
Requires-Dist: docopt==0.6.2
Requires-Dist: docstring-parser==0.15
Requires-Dist: google-api-python-client==2.97.0
Requires-Dist: google-auth==2.22.0
Requires-Dist: importlib-resources==6.0.1
Requires-Dist: Jinja2==3.1.4
Requires-Dist: kfp>=2.0.0
Requires-Dist: packaging==23.1
Requires-Dist: pipreqs==0.4.13
Requires-Dist: pydantic==2.4.0
Requires-Dist: PyYAML==6.0.1
Requires-Dist: yarg==0.1.9
